<?xml version="1.0"?>
<molpro xmlns="http://www.molpro.net/schema/molpro-output"
  xmlns:xsd="http://www.w3.org/1999/XMLSchema"
  xmlns:cml="http://www.xml-cml.org/schema"
  xmlns:stm="http://www.xml-cml.org/schema"
  xmlns:xhtml="http://www.w3.org/1999/xhtml">
 <job>
  <jobstep command="HF-SCF" commandset="SCFPRO">
   <cml:molecule>
    <cml:symmetry pointGroup="C1">
    </cml:symmetry>
    <cml:atomArray>
     <cml:atom id="a1" elementType="C" x3="-0.183240162703168E-07" y3="0.528310232943627E-01"
       z3="0.763861918112347"/>
     <cml:atom id="a2" elementType="H" x3="0.666630909368284" y3="-0.657755546942823"
       z3="1.20609483316671"/>
     <cml:atom id="a3" elementType="H" x3="0.322405066259104" y3="1.04369983370407"
       z3="1.00703665839882"/>
     <cml:atom id="a4" elementType="H" x3="-0.989035790636841" y3="-0.103116645667871"
       z3="1.14120601281177"/>
     <cml:atom id="a5" elementType="O" x3="0.423565654174723E-09" y3="-0.113336180640629"
       z3="-0.656450886117061"/>
     <cml:atom id="a6" elementType="H" x3="0.26468090314995E-07" y3="0.886849365885266"
       z3="-2.03116153085564"/>
    </cml:atomArray>
    <cml:bondArray>
     <cml:bond atomRefs2="a1 a2"/>
     <cml:bond atomRefs2="a1 a3"/>
     <cml:bond atomRefs2="a1 a4"/>
     <cml:bond atomRefs2="a1 a5"/>
    </cml:bondArray>
   </cml:molecule>
   <property name="Energy" method="RHF" principal="true" stateSymmetry="1" stateNumber="1"
     value="-114.879745724884"/>
   <property name="One-electron energy" method="RHF" value="-232.127207995227"/>
   <property name="Two-electron energy" method="RHF" value="79.435096895801"/>
   <property name="Kinetic energy" method="RHF" value="114.571853331179"/>
   <property name="Nuclear energy" method="RHF" value="37.8123653745426"/>
   <property name="Virial quotient" method="RHF" value="-1.00268733013173"/>
   <property name="Dipole moment" method="RHF" principal="true" stateSymmetry="1"
     stateNumber="1"
     value="0.218597238652906E-01 0.569700466439935 0.116603831307551"/>
   <time start="11:10:52" end="11:10:56" cpu="5.86" system="0.65" real="6.22"/>
   <storage units="megabyte" memory="0.0" sf="0.0" df="177.37" eaf="30.23" ga="0.0"/>
   <summary overall_method="HF/6-311G(D,P)"/>
  </jobstep>
  <jobstep command="OPTG" commandset="OPT">
   <gradient name="SCF GRADIENT" stateSymmetry="1" stateNumber="1"
     virial="0.349403405693157">
      0.006629349088  -0.035205236685   0.038829438257
     -0.010475359419   0.008964650071   0.003795088310
     -0.004056888906  -0.008984774907  -0.010628595488
      0.010830479442   0.000510499338  -0.003069308862
     -0.003282754692  -0.010916408716   0.073174919674
      0.000355174487   0.045631270900  -0.102101541889
   </gradient>
   <opt energy="-114.87974572" type="HF-SCF000" line="0.0" convergence="0.3"
     gradient="0.14602839577599"/>
   <jobstep command="HF-SCF" commandset="SCFPRO">
    <cml:molecule>
     <cml:symmetry pointGroup="C1">
     </cml:symmetry>
     <cml:atomArray>
      <cml:atom id="a1" elementType="C" x3="-0.890067966769835E-03" y3="0.45814787952387E-01"
        z3="0.760020652926526"/>
      <cml:atom id="a2" elementType="H" x3="0.666643725941623" y3="-0.683726072513964"
        z3="1.19064123289383"/>
      <cml:atom id="a3" elementType="H" x3="0.3269029704874" y3="1.02218943476426"
        z3="1.06034467819532"/>
      <cml:atom id="a4" elementType="H" x3="-0.985521161011663" y3="-0.1316540645156"
        z3="1.15608320055941"/>
      <cml:atom id="a5" elementType="O" x3="0.632254931193531E-03" y3="-0.102997256839719"
        z3="-0.668796281048522"/>
      <cml:atom id="a6" elementType="H" x3="-0.746199027833202E-02" y3="0.882322642800175"
        z3="-1.84222552413335"/>
     </cml:atomArray>
     <cml:bondArray>
      <cml:bond atomRefs2="a1 a2"/>
      <cml:bond atomRefs2="a1 a3"/>
      <cml:bond atomRefs2="a1 a4"/>
      <cml:bond atomRefs2="a1 a5"/>
     </cml:bondArray>
    </cml:molecule>
    <property name="Energy" method="RHF" principal="true" stateSymmetry="1" stateNumber="1"
      value="-114.922120023795"/>
    <property name="One-electron energy" method="RHF" value="-232.532313851224"/>
    <property name="Two-electron energy" method="RHF" value="79.6239419205554"/>
    <property name="Kinetic energy" method="RHF" value="114.550837703848"/>
    <property name="Nuclear energy" method="RHF" value="37.9862519068739"/>
    <property name="Virial quotient" method="RHF" value="-1.0032412012639"/>
    <property name="Dipole moment" method="RHF" principal="true" stateSymmetry="1"
      stateNumber="1"
      value="0.14182587305399E-01 0.625951992141238 0.969905911006852E-01"/>
    <time start="11:10:57" end="11:11:00" cpu="6.17" system="0.13" real="4.23"/>
    <storage units="megabyte" memory="0.0" sf="0.02" df="177.37" eaf="30.81" ga="0.0"/>
    <summary overall_method="HF/6-311G(D,P)"/>
   </jobstep>
   <gradient name="SCF GRADIENT" stateSymmetry="1" stateNumber="1"
     virial="0.414392614738671">
      0.003388513181  -0.025206145007   0.031008968199
     -0.006406680770   0.005074394061   0.006901146707
     -0.002839855714  -0.007888799432  -0.004848207788
      0.008083188245  -0.000744804324   0.001320200435
     -0.002827396339  -0.032539350655   0.081833126433
      0.000602231397   0.061304705358  -0.116215233985
   </gradient>
   <opt energy="-114.92212002" type="HF-SCF000" line="0.0" convergence="0.3"
     gradient="0.164049753645861"/>
   <jobstep command="HF-SCF" commandset="SCFPRO">
    <cml:molecule>
     <cml:symmetry pointGroup="C1">
     </cml:symmetry>
     <cml:atomArray>
      <cml:atom id="a1" elementType="C" x3="-0.387543237597655E-03" y3="0.324017628157388E-01"
        z3="0.765464021969503"/>
      <cml:atom id="a2" elementType="H" x3="0.662760426933216" y3="-0.689459168961254"
        z3="1.22190177871029"/>
      <cml:atom id="a3" elementType="H" x3="0.324570428098497" y3="1.01308516456724"
        z3="1.06061981336281"/>
      <cml:atom id="a4" elementType="H" x3="-0.985184821233406" y3="-0.137299822615877"
        z3="1.17513809311471"/>
      <cml:atom id="a5" elementType="O" x3="0.688258839062998E-03" y3="-0.814892733144763E-01"
        z3="-0.682989704413588"/>
      <cml:atom id="a6" elementType="H" x3="-0.845478713975505E-02" y3="0.721165146278202"
        z3="-1.73236949156499"/>
     </cml:atomArray>
     <cml:bondArray>
      <cml:bond atomRefs2="a1 a2"/>
      <cml:bond atomRefs2="a1 a3"/>
      <cml:bond atomRefs2="a1 a4"/>
      <cml:bond atomRefs2="a1 a5"/>
      <cml:bond atomRefs2="a5 a6"/>
     </cml:bondArray>
    </cml:molecule>
    <property name="Energy" method="RHF" principal="true" stateSymmetry="1" stateNumber="1"
      value="-114.969828796493"/>
    <property name="One-electron energy" method="RHF" value="-233.084024765481"/>
    <property name="Two-electron energy" method="RHF" value="79.8954547154435"/>
    <property name="Kinetic energy" method="RHF" value="114.570216026387"/>
    <property name="Nuclear energy" method="RHF" value="38.2187412535448"/>
    <property name="Virial quotient" method="RHF" value="-1.00348792892224"/>
    <property name="Dipole moment" method="RHF" principal="true" stateSymmetry="1"
      stateNumber="1"
      value="0.650114161069775E-02 0.602867363496722 0.805629603058959E-01"/>
    <time start="11:11:02" end="11:11:06" cpu="5.88" system="0.12" real="5.27"/>
    <storage units="megabyte" memory="0.0" sf="0.02" df="177.37" eaf="30.86" ga="0.0"/>
    <summary overall_method="HF/6-311G(D,P)"/>
   </jobstep>
   <gradient name="SCF GRADIENT" stateSymmetry="1" stateNumber="1"
     virial="0.453666275569722">
      0.003316018046  -0.034244178310   0.031946470560
     -0.005616877383   0.004928064387   0.013115203189
     -0.002343264770  -0.006683166460  -0.006074580488
      0.006251713798  -0.000041859633   0.005836445543
     -0.001644286029  -0.028517504827   0.090109221755
      0.000036696338   0.064558644843  -0.134932760559
   </gradient>
   <opt energy="-114.9698288" type="HF-SCF000" line="0.0" convergence="0.3"
     gradient="0.184126531879848"/>
   <jobstep command="HF-SCF" commandset="SCFPRO">
    <cml:molecule>
     <cml:symmetry pointGroup="C1">
     </cml:symmetry>
     <cml:atomArray>
      <cml:atom id="a1" elementType="C" x3="-0.742705841952024E-03" y3="0.265600814681529E-01"
        z3="0.770739645982275"/>
      <cml:atom id="a2" elementType="H" x3="0.674769762840035" y3="-0.698312519877001"
        z3="1.22441867539486"/>
      <cml:atom id="a3" elementType="H" x3="0.302924983889671" y3="0.999239693130407"
        z3="1.11289538851224"/>
      <cml:atom id="a4" elementType="H" x3="-0.978057793486528" y3="-0.187785338576107"
        z3="1.19253289664411"/>
      <cml:atom id="a5" elementType="O" x3="0.178458821105867E-02" y3="-0.697375257971766E-01"
        z3="-0.702572457111892"/>
      <cml:atom id="a6" elementType="H" x3="-0.191163844137883E-01" y3="0.677396672633675"
        z3="-1.5565803039429"/>
     </cml:atomArray>
     <cml:bondArray>
      <cml:bond atomRefs2="a1 a2"/>
      <cml:bond atomRefs2="a1 a3"/>
      <cml:bond atomRefs2="a1 a4"/>
      <cml:bond atomRefs2="a1 a5"/>
      <cml:bond atomRefs2="a5 a6"/>
     </cml:bondArray>
    </cml:molecule>
    <property name="Energy" method="RHF" principal="true" stateSymmetry="1" stateNumber="1"
      value="-115.021100542974"/>
    <property name="One-electron energy" method="RHF" value="-233.478653773293"/>
    <property name="Two-electron energy" method="RHF" value="80.0171319343336"/>
    <property name="Kinetic energy" method="RHF" value="114.636843434203"/>
    <property name="Nuclear energy" method="RHF" value="38.4404212959853"/>
    <property name="Virial quotient" method="RHF" value="-1.00335195123365"/>
    <property name="Dipole moment" method="RHF" principal="true" stateSymmetry="1"
      stateNumber="1"
      value="0.708259881696904E-02 0.598283750150912 0.203073159052142"/>
    <time start="11:11:08" end="11:11:11" cpu="5.68" system="0.12" real="5.3"/>
    <storage units="megabyte" memory="0.0" sf="0.02" df="177.37" eaf="30.89" ga="0.0"/>
    <summary overall_method="HF/6-311G(D,P)"/>
   </jobstep>
   <gradient name="SCF GRADIENT" stateSymmetry="1" stateNumber="1"
     virial="0.439838904784124">
      0.002313377834  -0.019769220522   0.033765462502
     -0.002847504834   0.000809864897   0.017432871995
     -0.002060029254  -0.007473132482  -0.000263513481
      0.003801191453  -0.001781992532   0.010602603045
     -0.001562368752  -0.031033212301   0.057855851241
      0.000355333554   0.059247692940  -0.119393275303
   </gradient>
   <opt energy="-115.02110054" type="HF-SCF000" line="0.0" convergence="0.3"
     gradient="0.155296878310232"/>
   <jobstep command="HF-SCF" commandset="SCFPRO">
    <cml:molecule>
     <cml:symmetry pointGroup="C1">
     </cml:symmetry>
     <cml:atomArray>
      <cml:atom id="a1" elementType="C" x3="-0.652038697606543E-03" y3="0.196287700692385E-01"
        z3="0.771259233362565"/>
      <cml:atom id="a2" elementType="H" x3="0.680438810886742" y3="-0.706448411388887"
        z3="1.22428141851169"/>
      <cml:atom id="a3" elementType="H" x3="0.296215223076638" y3="0.992469238733437"
        z3="1.12388065299271"/>
      <cml:atom id="a4" elementType="H" x3="-0.978055614808728" y3="-0.207197362185284"
        z3="1.1962048135576"/>
      <cml:atom id="a5" elementType="O" x3="0.20775439892753E-02" y3="-0.565435910456303E-01"
        z3="-0.713286512868806"/>
      <cml:atom id="a6" elementType="H" x3="-0.238068281127764E-01" y3="0.584847716862217"
        z3="-1.40724707041203"/>
     </cml:atomArray>
     <cml:bondArray>
      <cml:bond atomRefs2="a1 a2"/>
      <cml:bond atomRefs2="a1 a3"/>
      <cml:bond atomRefs2="a1 a4"/>
      <cml:bond atomRefs2="a1 a5"/>
      <cml:bond atomRefs2="a5 a6"/>
     </cml:bondArray>
    </cml:molecule>
    <property name="Energy" method="RHF" principal="true" stateSymmetry="1" stateNumber="1"
      value="-115.050652080733"/>
    <property name="One-electron energy" method="RHF" value="-234.707732771015"/>
    <property name="Two-electron energy" method="RHF" value="80.524262652232"/>
    <property name="Kinetic energy" method="RHF" value="114.875349873335"/>
    <property name="Nuclear energy" method="RHF" value="39.132818038049"/>
    <property name="Virial quotient" method="RHF" value="-1.00152602109671"/>
    <property name="Dipole moment" method="RHF" principal="true" stateSymmetry="1"
      stateNumber="1"
      value="0.253464221665525E-02 0.551665692737974 0.328877489193455"/>
    <time start="11:11:13" end="11:11:17" cpu="5.88" system="0.08" real="6.16"/>
    <storage units="megabyte" memory="0.0" sf="0.03" df="177.37" eaf="30.98" ga="0.0"/>
    <summary overall_method="HF/6-311G(D,P)"/>
   </jobstep>
   <gradient name="SCF GRADIENT" stateSymmetry="1" stateNumber="1"
     virial="0.227487627888207">
      0.002408441376  -0.016058432310   0.036689725787
     -0.001056190671  -0.001472249669   0.019573984432
     -0.001669721062  -0.006548061110   0.001073214433
      0.001349522092  -0.002366213114   0.012730144562
     -0.001656899901   0.044706798678  -0.037277127000
      0.000624848166  -0.018261842474  -0.032789942215
   </gradient>
   <opt energy="-115.05065208" type="HF-SCF000" line="0.0" convergence="0.3"
     gradient="0.837413897466735E-01"/>
   <jobstep command="HF-SCF" commandset="SCFPRO">
    <cml:molecule>
     <cml:symmetry pointGroup="C1">
     </cml:symmetry>
     <cml:atomArray>
      <cml:atom id="a1" elementType="C" x3="-0.175261113056451E-02" y3="0.210659337593411E-01"
        z3="0.755994410273033"/>
      <cml:atom id="a2" elementType="H" x3="0.709965165156468" y3="-0.745153528040233"
        z3="1.07582044375418"/>
      <cml:atom id="a3" elementType="H" x3="0.301553114915762" y3="0.969012443874892"
        z3="1.17680286337079"/>
      <cml:atom id="a4" elementType="H" x3="-0.985194082688412" y3="-0.251955787057283"
        z3="1.13262084263016"/>
      <cml:atom id="a5" elementType="O" x3="0.629556048516831E-03" y3="-0.564440580132715E-01"
        z3="-0.699107920594923"/>
      <cml:atom id="a6" elementType="H" x3="-0.154476650187824E-01" y3="0.673076329804187"
        z3="-1.29139318661516"/>
     </cml:atomArray>
     <cml:bondArray>
      <cml:bond atomRefs2="a1 a2"/>
      <cml:bond atomRefs2="a1 a3"/>
      <cml:bond atomRefs2="a1 a4"/>
      <cml:bond atomRefs2="a1 a5"/>
      <cml:bond atomRefs2="a5 a6"/>
     </cml:bondArray>
    </cml:molecule>
    <property name="Energy" method="RHF" principal="true" stateSymmetry="1" stateNumber="1"
      value="-115.063874748785"/>
    <property name="One-electron energy" method="RHF" value="-235.858847905058"/>
    <property name="Two-electron energy" method="RHF" value="81.0652471788454"/>
    <property name="Kinetic energy" method="RHF" value="114.968529926988"/>
    <property name="Nuclear energy" method="RHF" value="39.7297259774278"/>
    <property name="Virial quotient" method="RHF" value="-1.00082931235059"/>
    <property name="Dipole moment" method="RHF" principal="true" stateSymmetry="1"
      stateNumber="1"
      value="0.171201114069577E-01 0.614667852219078 0.293143649348668"/>
    <time start="11:11:19" end="11:11:23" cpu="5.3" system="0.13" real="5.56"/>
    <storage units="megabyte" memory="0.0" sf="0.03" df="177.37" eaf="31.11" ga="0.0"/>
    <summary overall_method="HF/6-311G(D,P)"/>
   </jobstep>
   <gradient name="SCF GRADIENT" stateSymmetry="1" stateNumber="1"
     virial="0.143693959741676">
     -0.003290810658   0.009593161473   0.034000033123
      0.004844567026  -0.006719043277   0.001529897409
     -0.000483124621  -0.004719611895   0.005421206843
     -0.001687888457  -0.003334265382   0.003125908479
     -0.000719920042   0.020264800218  -0.022709738689
      0.001337176751  -0.015085041137  -0.021367307165
   </gradient>
   <opt energy="-115.06387475" type="HF-SCF000" line="0.0" convergence="0.3"
     gradient="0.549388076521187E-01"/>
   <jobstep command="HF-SCF" commandset="SCFPRO">
    <cml:molecule>
     <cml:symmetry pointGroup="C1">
     </cml:symmetry>
     <cml:atomArray>
      <cml:atom id="a1" elementType="C" x3="-0.298561469222756E-03" y3="0.162126638799491E-01"
        z3="0.73114562465924"/>
      <cml:atom id="a2" elementType="H" x3="0.663036894536385" y3="-0.781861116842251"
        z3="1.05351100022879"/>
      <cml:atom id="a3" elementType="H" x3="0.355613438483106" y3="0.966099743558424"
        z3="1.12272009485374"/>
      <cml:atom id="a4" elementType="H" x3="-1.00743215237344" y3="-0.167532923122463"
        z3="1.08895251886309"/>
      <cml:atom id="a5" elementType="O" x3="-0.920881344383543E-03" y3="-0.606860226208562E-01"
        z3="-0.681039671083591"/>
      <cml:atom id="a6" elementType="H" x3="0.69517911791803E-02" y3="0.753383849175045"
        z3="-1.16221856594547"/>
     </cml:atomArray>
     <cml:bondArray>
      <cml:bond atomRefs2="a1 a2"/>
      <cml:bond atomRefs2="a1 a3"/>
      <cml:bond atomRefs2="a1 a4"/>
      <cml:bond atomRefs2="a1 a5"/>
      <cml:bond atomRefs2="a5 a6"/>
     </cml:bondArray>
    </cml:molecule>
    <property name="Energy" method="RHF" principal="true" stateSymmetry="1" stateNumber="1"
      value="-115.071731142581"/>
    <property name="One-electron energy" method="RHF" value="-237.320040940424"/>
    <property name="Two-electron energy" method="RHF" value="81.7549434672881"/>
    <property name="Kinetic energy" method="RHF" value="115.06796408923"/>
    <property name="Nuclear energy" method="RHF" value="40.4933663305544"/>
    <property name="Virial quotient" method="RHF" value="-1.00003273763798"/>
    <property name="Dipole moment" method="RHF" principal="true" stateSymmetry="1"
      stateNumber="1"
      value="0.244283473173575E-03 0.655823375433254 0.272289035754711"/>
    <time start="11:11:24" end="11:11:27" cpu="5.21" system="0.11" real="3.86"/>
    <storage units="megabyte" memory="0.0" sf="0.03" df="177.37" eaf="31.19" ga="0.0"/>
    <summary overall_method="HF/6-311G(D,P)"/>
   </jobstep>
   <gradient name="SCF GRADIENT" stateSymmetry="1" stateNumber="1"
     virial="0.488622275875342E-01">
     -0.000989721727   0.003069216488   0.016891709913
      0.003568451042  -0.004046772640  -0.005345411506
     -0.000579392253   0.000739560643   0.002120659670
     -0.000887749699  -0.000942749700  -0.004372885460
     -0.002805850985   0.000859738971   0.006797355156
      0.001694263622   0.000321006238  -0.016091427773
   </gradient>
   <opt energy="-115.07173114" type="HF-SCF000" line="0.0"
     convergence="0.241783658177815" gradient="0.263877925383433E-01"/>
   <jobstep command="HF-SCF" commandset="SCFPRO">
    <cml:molecule>
     <cml:symmetry pointGroup="C1">
     </cml:symmetry>
     <cml:atomArray>
      <cml:atom id="a1" elementType="C" x3="-0.81593277761165E-03" y3="0.126862376561658E-01"
        z3="0.712499082385459"/>
      <cml:atom id="a2" elementType="H" x3="0.613541760952369" y3="-0.798062817177495"
        z3="1.07885953450941"/>
      <cml:atom id="a3" elementType="H" x3="0.413835209948104" y3="0.952913766635976"
        z3="1.07535599377713"/>
      <cml:atom id="a4" elementType="H" x3="-1.00581939470835" y3="-0.977439804400895E-01"
        z3="1.10319144458784"/>
      <cml:atom id="a5" elementType="O" x3="-0.479316061716434E-03" y3="-0.63337412409762E-01"
        z3="-0.673356009915393"/>
      <cml:atom id="a6" elementType="H" x3="-0.42353123069755E-02" y3="0.797050607200731"
        z3="-1.05436598070776"/>
     </cml:atomArray>
     <cml:bondArray>
      <cml:bond atomRefs2="a1 a2"/>
      <cml:bond atomRefs2="a1 a3"/>
      <cml:bond atomRefs2="a1 a4"/>
      <cml:bond atomRefs2="a1 a5"/>
      <cml:bond atomRefs2="a5 a6"/>
     </cml:bondArray>
    </cml:molecule>
    <property name="Energy" method="RHF" principal="true" stateSymmetry="1" stateNumber="1"
      value="-115.074156065687"/>
    <property name="One-electron energy" method="RHF" value="-238.273544211786"/>
    <property name="Two-electron energy" method="RHF" value="82.1888048132597"/>
    <property name="Kinetic energy" method="RHF" value="115.147724187179"/>
    <property name="Nuclear energy" method="RHF" value="41.0105833328392"/>
    <property name="Virial quotient" method="RHF" value="-0.999361097911298"/>
    <property name="Dipole moment" method="RHF" principal="true" stateSymmetry="1"
      stateNumber="1"
      value="-0.430774547770364E-01 0.665383889206384 0.285124752044019"/>
    <time start="11:11:28" end="11:11:31" cpu="5.72" system="0.12" real="4.86"/>
    <storage units="megabyte" memory="0.0" sf="0.03" df="177.37" eaf="31.27" ga="0.0"/>
    <summary overall_method="HF/6-311G(D,P)"/>
   </jobstep>
   <gradient name="SCF GRADIENT" stateSymmetry="1" stateNumber="1"
     virial="-0.319285289335361E-01">
     -0.001516978024  -0.002592086336  -0.005158339839
      0.000285041323   0.000333062859  -0.003974049287
     -0.000109634803   0.001711924848  -0.000569193783
      0.001715220190  -0.000303930515  -0.002712471784
     -0.002147710710  -0.001960816392   0.014966137481
      0.001774062023   0.002811845536  -0.002552082789
   </gradient>
   <opt energy="-115.07415607" type="HF-SCF000" line="0.0"
     convergence="0.67279303933836E-01" gradient="0.177561827958935E-01"/>
   <jobstep command="HF-SCF" commandset="SCFPRO">
    <cml:molecule>
     <cml:symmetry pointGroup="C1">
     </cml:symmetry>
     <cml:atomArray>
      <cml:atom id="a1" elementType="C" x3="-0.692242501265381E-03" y3="0.122761876656366E-01"
        z3="0.714519556649144"/>
      <cml:atom id="a2" elementType="H" x3="0.568439240418392" y3="-0.822854827132092"
        z3="1.10147418780163"/>
      <cml:atom id="a3" elementType="H" x3="0.459643910113092" y3="0.92922524261763"
        z3="1.07677143846882"/>
      <cml:atom id="a4" elementType="H" x3="-1.01041663632675" y3="-0.411796055617896E-01"
        z3="1.11061168799462"/>
      <cml:atom id="a5" elementType="O" x3="-0.485899123270141E-03" y3="-0.636488743343691E-01"
        z3="-0.677260917626745"/>
      <cml:atom id="a6" elementType="H" x3="-0.171253135952484E-02" y3="0.798792286935235"
        z3="-1.04790006060748"/>
     </cml:atomArray>
     <cml:bondArray>
      <cml:bond atomRefs2="a1 a2"/>
      <cml:bond atomRefs2="a1 a3"/>
      <cml:bond atomRefs2="a1 a4"/>
      <cml:bond atomRefs2="a1 a5"/>
      <cml:bond atomRefs2="a5 a6"/>
     </cml:bondArray>
    </cml:molecule>
    <property name="Energy" method="RHF" principal="true" stateSymmetry="1" stateNumber="1"
      value="-115.074535477197"/>
    <property name="One-electron energy" method="RHF" value="-238.070239028661"/>
    <property name="Two-electron energy" method="RHF" value="82.085631752513"/>
    <property name="Kinetic energy" method="RHF" value="115.134073115608"/>
    <property name="Nuclear energy" method="RHF" value="40.910071798952"/>
    <property name="Virial quotient" method="RHF" value="-0.999482884286116"/>
    <property name="Dipole moment" method="RHF" principal="true" stateSymmetry="1"
      stateNumber="1"
      value="-0.714967799019492E-01 0.662143938679486 0.302044007933758"/>
    <time start="11:11:33" end="11:11:37" cpu="5.66" system="0.1" real="5.07"/>
    <storage units="megabyte" memory="0.0" sf="0.04" df="177.37" eaf="31.27" ga="0.0"/>
    <summary overall_method="HF/6-311G(D,P)"/>
   </jobstep>
   <gradient name="SCF GRADIENT" stateSymmetry="1" stateNumber="1"
     virial="-0.181597326254381E-01">
      0.000269198672  -0.002400618103  -0.004096446370
      0.000262571672   0.000956560293  -0.000638498795
     -0.000614537994   0.000325308088  -0.000094436444
      0.000989855606   0.000011401752  -0.000893143909
     -0.002712719711   0.000530070838   0.006415764744
      0.001805631755   0.000577277131  -0.000693239227
   </gradient>
   <opt energy="-115.07453548" type="HF-SCF000" line="0.0"
     convergence="0.133729884041168" gradient="0.889685264978824E-02"/>
   <jobstep command="HF-SCF" commandset="SCFPRO">
    <cml:molecule>
     <cml:symmetry pointGroup="C1">
     </cml:symmetry>
     <cml:atomArray>
      <cml:atom id="a1" elementType="C" x3="-0.668273589802495E-03" y3="0.120945890781726E-01"
        z3="0.717906326201322"/>
      <cml:atom id="a2" elementType="H" x3="0.465973723715364" y3="-0.88087873813037"
        z3="1.11804392987586"/>
      <cml:atom id="a3" elementType="H" x3="0.564748482128453" y3="0.867868294161444"
        z3="1.07773455873985"/>
      <cml:atom id="a4" elementType="H" x3="-1.0100190771873" y3="0.790985336961084E-01"
        z3="1.12157580020198"/>
      <cml:atom id="a5" elementType="O" x3="-0.767549108961964E-03" y3="-0.644681592476248E-01"
        z3="-0.682462958122264"/>
      <cml:atom id="a6" elementType="H" x3="-0.564551030388399E-03" y3="0.813059913242931"
        z3="-1.03416258481799"/>
     </cml:atomArray>
     <cml:bondArray>
      <cml:bond atomRefs2="a1 a2"/>
      <cml:bond atomRefs2="a1 a3"/>
      <cml:bond atomRefs2="a1 a4"/>
      <cml:bond atomRefs2="a1 a5"/>
      <cml:bond atomRefs2="a5 a6"/>
     </cml:bondArray>
    </cml:molecule>
    <property name="Energy" method="RHF" principal="true" stateSymmetry="1" stateNumber="1"
      value="-115.074827932646"/>
    <property name="One-electron energy" method="RHF" value="-237.703073310364"/>
    <property name="Two-electron energy" method="RHF" value="81.9063013938571"/>
    <property name="Kinetic energy" method="RHF" value="115.095256164894"/>
    <property name="Nuclear energy" method="RHF" value="40.7219439838609"/>
    <property name="Virial quotient" method="RHF" value="-0.999822510215204"/>
    <property name="Dipole moment" method="RHF" principal="true" stateSymmetry="1"
      stateNumber="1"
      value="-0.142722228315605 0.652164579700476 0.323699354254064"/>
    <time start="11:11:39" end="11:11:43" cpu="6.32" system="0.16" real="6.31"/>
    <storage units="megabyte" memory="0.0" sf="0.04" df="177.37" eaf="31.27" ga="0.0"/>
    <summary overall_method="HF/6-311G(D,P)"/>
   </jobstep>
   <gradient name="SCF GRADIENT" stateSymmetry="1" stateNumber="1"
     virial="0.208551878482738E-01">
      0.000611857072  -0.000417482874  -0.001899233755
      0.000719466164   0.000743194435   0.002235938590
     -0.000774945228  -0.000532571603   0.000038286051
     -0.000361579671   0.000032750932   0.001484090808
     -0.000267788832  -0.007527939816   0.000552894697
      0.000072990495   0.007702048925  -0.002411976393
   </gradient>
   <opt energy="-115.07482793" type="HF-SCF000" line="0.0"
     convergence="0.105091723871383" gradient="0.116463261971521E-01"/>
   <jobstep command="HF-SCF" commandset="SCFPRO">
    <cml:molecule>
     <cml:symmetry pointGroup="C1">
     </cml:symmetry>
     <cml:atomArray>
      <cml:atom id="a1" elementType="C" x3="-0.51537097341326E-03" y3="0.122949252045856E-01"
        z3="0.72099247718458"/>
      <cml:atom id="a2" elementType="H" x3="0.379560825766288" y3="-0.922548850637542"
        z3="1.11683167024625"/>
      <cml:atom id="a3" elementType="H" x3="0.641623491176659" y3="0.811325138062943"
        z3="1.08178833174413"/>
      <cml:atom id="a4" elementType="H" x3="-1.00278978871787" y3="0.170632918102719"
        z3="1.11885630822407"/>
      <cml:atom id="a5" elementType="O" x3="-0.772026651781064E-03" y3="-0.642298903349225E-01"
        z3="-0.684750066584846"/>
      <cml:atom id="a6" elementType="H" x3="-0.547407996764279E-05" y3="0.813571929849477"
        z3="-1.03473281674717"/>
     </cml:atomArray>
     <cml:bondArray>
      <cml:bond atomRefs2="a1 a2"/>
      <cml:bond atomRefs2="a1 a3"/>
      <cml:bond atomRefs2="a1 a4"/>
      <cml:bond atomRefs2="a1 a5"/>
      <cml:bond atomRefs2="a5 a6"/>
     </cml:bondArray>
    </cml:molecule>
    <property name="Energy" method="RHF" principal="true" stateSymmetry="1" stateNumber="1"
      value="-115.075087104362"/>
    <property name="One-electron energy" method="RHF" value="-237.548072764331"/>
    <property name="Two-electron energy" method="RHF" value="81.8320658254643"/>
    <property name="Kinetic energy" method="RHF" value="115.084441228617"/>
    <property name="Nuclear energy" method="RHF" value="40.640919834504"/>
    <property name="Virial quotient" method="RHF" value="-0.99991871947107"/>
    <property name="Dipole moment" method="RHF" principal="true" stateSymmetry="1"
      stateNumber="1"
      value="-0.19787626025968 0.634179553784214 0.331859878305281"/>
    <time start="11:11:45" end="11:11:49" cpu="5.19" system="0.09" real="5.94"/>
    <storage units="megabyte" memory="0.0" sf="0.04" df="177.37" eaf="31.27" ga="0.0"/>
    <summary overall_method="HF/6-311G(D,P)"/>
   </jobstep>
   <gradient name="SCF GRADIENT" stateSymmetry="1" stateNumber="1"
     virial="0.319893003223453E-01">
      0.000812192862   0.000617043836   0.002288292382
      0.000831624274   0.000398035326   0.002281694039
     -0.000682094854  -0.000575650510  -0.000093549521
     -0.001046022165  -0.000132876646   0.001401886094
      0.000558935458  -0.007143985236  -0.003634592898
     -0.000474635574   0.006837433231  -0.002243730095
   </gradient>
   <opt energy="-115.0750871" type="HF-SCF000" line="0.0"
     convergence="0.150752796702572" gradient="0.115232208603747E-01"/>
   <jobstep command="HF-SCF" commandset="SCFPRO">
    <cml:molecule>
     <cml:symmetry pointGroup="C1">
     </cml:symmetry>
     <cml:atomArray>
      <cml:atom id="a1" elementType="C" x3="-0.302814427509857E-03" y3="0.128186705801379E-01"
        z3="0.722014897468432"/>
      <cml:atom id="a2" elementType="H" x3="0.256048474962829" y3="-0.968745139791653"
        z3="1.09977388313967"/>
      <cml:atom id="a3" elementType="H" x3="0.736078030770123" y3="0.723704846450198"
        z3="1.08965292758701"/>
      <cml:atom id="a4" elementType="H" x3="-0.980614663324828" y3="0.287701441293137"
        z3="1.10917880347577"/>
      <cml:atom id="a5" elementType="O" x3="-0.282812138210071E-03" y3="-0.634008053755388E-01"
        z3="-0.684184644126622"/>
      <cml:atom id="a6" elementType="H" x3="-0.341785007047079E-02" y3="0.810925664190908"
        z3="-1.03700956670792"/>
     </cml:atomArray>
     <cml:bondArray>
      <cml:bond atomRefs2="a1 a2"/>
      <cml:bond atomRefs2="a1 a3"/>
      <cml:bond atomRefs2="a1 a4"/>
      <cml:bond atomRefs2="a1 a5"/>
      <cml:bond atomRefs2="a5 a6"/>
     </cml:bondArray>
    </cml:molecule>
    <property name="Energy" method="RHF" principal="true" stateSymmetry="1" stateNumber="1"
      value="-115.075474257266"/>
    <property name="One-electron energy" method="RHF" value="-237.590055463784"/>
    <property name="Two-electron energy" method="RHF" value="81.8535858019833"/>
    <property name="Kinetic energy" method="RHF" value="115.091523438384"/>
    <property name="Nuclear energy" method="RHF" value="40.6609954045353"/>
    <property name="Virial quotient" method="RHF" value="-0.999860552883144"/>
    <property name="Dipole moment" method="RHF" principal="true" stateSymmetry="1"
      stateNumber="1"
      value="-0.2725916539629 0.59963636066484 0.327717538654017"/>
    <time start="11:11:51" end="11:11:53" cpu="4.78" system="0.11" real="4.15"/>
    <storage units="megabyte" memory="0.0" sf="0.04" df="177.37" eaf="31.28" ga="0.0"/>
    <summary overall_method="HF/6-311G(D,P)"/>
   </jobstep>
   <gradient name="SCF GRADIENT" stateSymmetry="1" stateNumber="1"
     virial="0.250940470327387E-01">
      0.000136007164   0.001798669356   0.005284914172
      0.000584220101  -0.000090315825   0.000168669753
     -0.000226609435   0.000072792971  -0.000187108414
     -0.000926421029  -0.000552170962   0.000232662548
      0.000885003684  -0.005270094238  -0.004183494081
     -0.000452200486   0.004041118698  -0.001315643979
   </gradient>
   <opt energy="-115.07547426" type="HF-SCF000" line="0.0"
     convergence="0.132398805218862" gradient="0.985878693062631E-02"/>
   <jobstep command="HF-SCF" commandset="SCFPRO">
    <cml:molecule>
     <cml:symmetry pointGroup="C1">
     </cml:symmetry>
     <cml:atomArray>
      <cml:atom id="a1" elementType="C" x3="-0.327657110938153E-03" y3="0.129299541377601E-01"
        z3="0.71938202096816"/>
      <cml:atom id="a2" elementType="H" x3="0.136424922149803" y3="-0.993327956403564"
        z3="1.09239924759257"/>
      <cml:atom id="a3" elementType="H" x3="0.814505737041719" y3="0.631193869390083"
        z3="1.09154697839918"/>
      <cml:atom id="a4" elementType="H" x3="-0.94176540904253" y3="0.400720050653323"
        z3="1.10376250550249"/>
      <cml:atom id="a5" elementType="O" x3="-0.224381953902999E-03" y3="-0.634805110386307E-01"
        z3="-0.681634706478408"/>
      <cml:atom id="a6" elementType="H" x3="-0.170278941467673E-02" y3="0.814940800593814"
        z3="-1.03523282408906"/>
     </cml:atomArray>
     <cml:bondArray>
      <cml:bond atomRefs2="a1 a2"/>
      <cml:bond atomRefs2="a1 a3"/>
      <cml:bond atomRefs2="a1 a4"/>
      <cml:bond atomRefs2="a1 a5"/>
      <cml:bond atomRefs2="a5 a6"/>
     </cml:bondArray>
    </cml:molecule>
    <property name="Energy" method="RHF" principal="true" stateSymmetry="1" stateNumber="1"
      value="-115.075653162099"/>
    <property name="One-electron energy" method="RHF" value="-237.72348939569"/>
    <property name="Two-electron energy" method="RHF" value="81.9189457315123"/>
    <property name="Kinetic energy" method="RHF" value="115.095801826059"/>
    <property name="Nuclear energy" method="RHF" value="40.728890502079"/>
    <property name="Virial quotient" method="RHF" value="-0.999824940061753"/>
    <property name="Dipole moment" method="RHF" principal="true" stateSymmetry="1"
      stateNumber="1"
      value="-0.338684127571237 0.562968555331129 0.316500146250942"/>
    <time start="11:11:54" end="11:11:58" cpu="5.39" system="0.1" real="5.07"/>
    <storage units="megabyte" memory="0.0" sf="0.05" df="177.37" eaf="31.28" ga="0.0"/>
    <summary overall_method="HF/6-311G(D,P)"/>
   </jobstep>
   <gradient name="SCF GRADIENT" stateSymmetry="1" stateNumber="1"
     virial="0.205757546530446E-01">
     -0.001002911120   0.000890245269   0.002838155131
      0.000451581758  -0.000057151012  -0.000749212018
      0.000046416007   0.000396775290  -0.000358410821
     -0.000207612556  -0.000212487431  -0.000170632220
      0.004017641196  -0.008215580236   0.001651118325
     -0.003305115284   0.007198198120  -0.003211018397
   </gradient>
   <opt energy="-115.07565316" type="HF-SCF000" line="0.0"
     convergence="0.919351086948424E-01" gradient="0.130552399052107E-01"/>
   <jobstep command="HF-SCF" commandset="SCFPRO">
    <cml:molecule>
     <cml:symmetry pointGroup="C1">
     </cml:symmetry>
     <cml:atomArray>
      <cml:atom id="a1" elementType="C" x3="-0.593524441123507E-03" y3="0.132161758621874E-01"
        z3="0.712332815028272"/>
      <cml:atom id="a2" elementType="H" x3="0.790830555565148E-01" y3="-1.00005790239377"
        z3="1.07649531400398"/>
      <cml:atom id="a3" elementType="H" x3="0.843909805494924" y3="0.587395057015247"
        z3="1.09395966242357"/>
      <cml:atom id="a4" elementType="H" x3="-0.919075352321756" y3="0.44689546873547"
        z3="1.09203519246301"/>
      <cml:atom id="a5" elementType="O" x3="0.614955703628482E-03" y3="-0.615967725276458E-01"
        z3="-0.673857674818176"/>
      <cml:atom id="a6" elementType="H" x3="-0.661030543550245E-02" y3="0.785989858248404"
        z3="-1.04950767571295"/>
     </cml:atomArray>
     <cml:bondArray>
      <cml:bond atomRefs2="a1 a2"/>
      <cml:bond atomRefs2="a1 a3"/>
      <cml:bond atomRefs2="a1 a4"/>
      <cml:bond atomRefs2="a1 a5"/>
      <cml:bond atomRefs2="a5 a6"/>
     </cml:bondArray>
    </cml:molecule>
    <property name="Energy" method="RHF" principal="true" stateSymmetry="1" stateNumber="1"
      value="-115.075431492792"/>
    <property name="One-electron energy" method="RHF" value="-238.392701348977"/>
    <property name="Two-electron energy" method="RHF" value="82.2359144447117"/>
    <property name="Kinetic energy" method="RHF" value="115.172875076352"/>
    <property name="Nuclear energy" method="RHF" value="41.0813554114732"/>
    <property name="Virial quotient" method="RHF" value="-0.999153936345731"/>
    <property name="Dipole moment" method="RHF" principal="true" stateSymmetry="1"
      stateNumber="1"
      value="-0.362725404698514 0.528246560199372 0.285242694487239"/>
    <time start="11:12:00" end="11:12:03" cpu="5.48" system="0.1" real="5.11"/>
    <storage units="megabyte" memory="0.0" sf="0.05" df="177.37" eaf="31.29" ga="0.0"/>
    <summary overall_method="HF/6-311G(D,P)"/>
   </jobstep>
   <gradient name="SCF GRADIENT" stateSymmetry="1" stateNumber="1"
     virial="-0.579089820359415E-01">
     -0.000963126599  -0.002662776169  -0.003708239933
     -0.000303352730   0.000470872979  -0.002790892914
      0.000177927937   0.001079399407  -0.000372267656
      0.002633655277   0.000090450992  -0.001922391681
     -0.009469285758   0.012545140731   0.002817305498
      0.007924181873  -0.011523087940   0.005976486686
   </gradient>
   <opt energy="-115.07543149" type="HF-SCF000" line="0.0"
     convergence="0.656024554685213E-01" gradient="0.229809674016249E-01"/>
   <jobstep command="HF-SCF" commandset="SCFPRO">
    <cml:molecule>
     <cml:symmetry pointGroup="C1">
     </cml:symmetry>
     <cml:atomArray>
      <cml:atom id="a1" elementType="C" x3="-0.338335182557738E-03" y3="0.132581231430286E-01"
        z3="0.715220258712326"/>
      <cml:atom id="a2" elementType="H" x3="0.245410841978692E-01" y3="-0.99997404629475"
        z3="1.09219315687169"/>
      <cml:atom id="a3" elementType="H" x3="0.873537276765733" y3="0.539150702842029"
        z3="1.09778767799671"/>
      <cml:atom id="a4" elementType="H" x3="-0.894554736723738" y3="0.498961011648799"
        z3="1.09835220003303"/>
      <cml:atom id="a5" elementType="O" x3="0.314178124092909E-04" y3="-0.631372454790797E-01"
        z3="-0.67810600991733"/>
      <cml:atom id="a6" elementType="H" x3="0.625159057201515E-05" y3="0.806033771656519"
        z3="-1.04230669646084"/>
     </cml:atomArray>
     <cml:bondArray>
      <cml:bond atomRefs2="a1 a2"/>
      <cml:bond atomRefs2="a1 a3"/>
      <cml:bond atomRefs2="a1 a4"/>
      <cml:bond atomRefs2="a1 a5"/>
      <cml:bond atomRefs2="a5 a6"/>
     </cml:bondArray>
    </cml:molecule>
    <property name="Energy" method="RHF" principal="true" stateSymmetry="1" stateNumber="1"
      value="-115.075786649303"/>
    <property name="One-electron energy" method="RHF" value="-237.981211403593"/>
    <property name="Two-electron energy" method="RHF" value="82.0406320943039"/>
    <property name="Kinetic energy" method="RHF" value="115.119229847071"/>
    <property name="Nuclear energy" method="RHF" value="40.8647926599863"/>
    <property name="Virial quotient" method="RHF" value="-0.999622624318926"/>
    <property name="Dipole moment" method="RHF" principal="true" stateSymmetry="1"
      stateNumber="1"
      value="-0.39227921986912 0.519577144047293 0.298813524048952"/>
    <time start="11:12:05" end="11:12:09" cpu="5.61" system="0.1" real="6.11"/>
    <storage units="megabyte" memory="0.0" sf="0.05" df="177.37" eaf="31.29" ga="0.0"/>
    <summary overall_method="HF/6-311G(D,P)"/>
   </jobstep>
   <gradient name="SCF GRADIENT" stateSymmetry="1" stateNumber="1"
     virial="-0.335633355657694E-02">
     -0.000641689908  -0.001001117307  -0.002265047490
     -0.000031326841   0.000395565646  -0.000516686019
      0.000195167191   0.000303278790   0.000229020226
      0.000799430254   0.000080693359  -0.000229783502
      0.001175304393  -0.002160708227   0.004679608144
     -0.001496885089   0.002382287738  -0.001897111360
   </gradient>
   <opt energy="-115.07578665" type="HF-SCF000" line="0.0"
     convergence="0.311486202929056E-01" gradient="0.687848117283532E-02"/>
   <jobstep command="HF-SCF" commandset="SCFPRO">
    <cml:molecule>
     <cml:symmetry pointGroup="C1">
     </cml:symmetry>
     <cml:atomArray>
      <cml:atom id="a1" elementType="C" x3="-0.170744998763921E-03" y3="0.129801512346115E-01"
        z3="0.716901320597607"/>
      <cml:atom id="a2" elementType="H" x3="0.501043506207809E-01" y3="-0.998598102309893"
        z3="1.0975347737475"/>
      <cml:atom id="a3" elementType="H" x3="0.860187069615557" y3="0.561495100241092"
        z3="1.09594816321984"/>
      <cml:atom id="a4" elementType="H" x3="-0.905968948923527" y3="0.478168517575745"
        z3="1.10131417882002"/>
      <cml:atom id="a5" elementType="O" x3="-0.153778502922194E-03" y3="-0.63040787153456E-01"
        z3="-0.67992220729339"/>
      <cml:atom id="a6" elementType="H" x3="0.151136009236504E-03" y3="0.804884825111067"
        z3="-1.03996253092606"/>
     </cml:atomArray>
     <cml:bondArray>
      <cml:bond atomRefs2="a1 a2"/>
      <cml:bond atomRefs2="a1 a3"/>
      <cml:bond atomRefs2="a1 a4"/>
      <cml:bond atomRefs2="a1 a5"/>
      <cml:bond atomRefs2="a5 a6"/>
     </cml:bondArray>
    </cml:molecule>
    <property name="Energy" method="RHF" principal="true" stateSymmetry="1" stateNumber="1"
      value="-115.075800190108"/>
    <property name="One-electron energy" method="RHF" value="-237.89310971427"/>
    <property name="Two-electron energy" method="RHF" value="81.9967781264193"/>
    <property name="Kinetic energy" method="RHF" value="115.116034652809"/>
    <property name="Nuclear energy" method="RHF" value="40.8205313977427"/>
    <property name="Virial quotient" method="RHF" value="-0.999650487763743"/>
    <property name="Dipole moment" method="RHF" principal="true" stateSymmetry="1"
      stateNumber="1"
      value="-0.379169760091868 0.529362894895922 0.307618696663639"/>
    <time start="11:12:11" end="11:12:15" cpu="5.47" system="0.12" real="5.9"/>
    <storage units="megabyte" memory="0.0" sf="0.05" df="177.37" eaf="31.29" ga="0.0"/>
    <summary overall_method="HF/6-311G(D,P)"/>
   </jobstep>
   <gradient name="SCF GRADIENT" stateSymmetry="1" stateNumber="1"
     virial="-0.150495928016301E-04">
     -0.000005979786  -0.000434197140  -0.000487970064
      0.000083059446   0.000179653833   0.000237730384
     -0.000097759300  -0.000016490515   0.000045044143
      0.000088695081   0.000065746296   0.000181747138
     -0.000258226285   0.000003121288   0.000182834992
      0.000190210843   0.000202166238  -0.000159386592
   </gradient>
   <opt energy="-115.07580019" type="HF-SCF000" line="0.0"
     convergence="0.23845716123589E-01" gradient="0.884319875182715E-03"/>
   <jobstep command="HF-SCF" commandset="SCFPRO">
    <cml:molecule>
     <cml:symmetry pointGroup="C1">
     </cml:symmetry>
     <cml:atomArray>
      <cml:atom id="a1" elementType="C" x3="-0.672313668375809E-04" y3="0.130288486691093E-01"
        z3="0.716788810120369"/>
      <cml:atom id="a2" elementType="H" x3="0.291997116975926E-01" y3="-0.999808315840216"
        z3="1.09638675346236"/>
      <cml:atom id="a3" elementType="H" x3="0.870398176063568" y3="0.544772627983558"
        z3="1.09711611815523"/>
      <cml:atom id="a4" elementType="H" x3="-0.897895192241166" y3="0.495110860531623"
        z3="1.09943074759475"/>
      <cml:atom id="a5" elementType="O" x3="-0.231999843161414E-04" y3="-0.630523904058638E-01"
        z3="-0.679752428845872"/>
      <cml:atom id="a6" elementType="H" x3="-0.533982635130136E-03" y3="0.805479487903353"
        z3="-1.03945389780564"/>
     </cml:atomArray>
     <cml:bondArray>
      <cml:bond atomRefs2="a1 a2"/>
      <cml:bond atomRefs2="a1 a3"/>
      <cml:bond atomRefs2="a1 a4"/>
      <cml:bond atomRefs2="a1 a5"/>
      <cml:bond atomRefs2="a5 a6"/>
     </cml:bondArray>
    </cml:molecule>
    <property name="Energy" method="RHF" principal="true" stateSymmetry="1" stateNumber="1"
      value="-115.075807788385"/>
    <property name="One-electron energy" method="RHF" value="-237.898467224641"/>
    <property name="Two-electron energy" method="RHF" value="81.9996049433711"/>
    <property name="Kinetic energy" method="RHF" value="115.115584943442"/>
    <property name="Nuclear energy" method="RHF" value="40.8230544928847"/>
    <property name="Virial quotient" method="RHF" value="-0.999654458993745"/>
    <property name="Dipole moment" method="RHF" principal="true" stateSymmetry="1"
      stateNumber="1"
      value="-0.389766297040923 0.52193033091499 0.306603301328585"/>
    <time start="11:12:17" end="11:12:20" cpu="5.19" system="0.09" real="5.15"/>
    <storage units="megabyte" memory="0.0" sf="0.06" df="177.37" eaf="31.29" ga="0.0"/>
    <summary overall_method="HF/6-311G(D,P)"/>
   </jobstep>
   <gradient name="SCF GRADIENT" stateSymmetry="1" stateNumber="1"
     virial="0.447831570748888E-03">
      0.000095074009  -0.000176123989  -0.000589376342
      0.000040084754   0.000029021935   0.000097261259
     -0.000019507643   0.000099835347   0.000059609609
     -0.000013529104  -0.000028072762   0.000062370911
      0.000073310896  -0.000448407628   0.000692922039
     -0.000175432913   0.000523747096  -0.000322787477
   </gradient>
   <opt energy="-115.07580779" type="HF-SCF000" line="0.0"
     convergence="0.265505220948894E-01" gradient="0.123043022214505E-02"/>
   <jobstep command="HF-SCF" commandset="SCFPRO">
    <cml:molecule>
     <cml:symmetry pointGroup="C1">
     </cml:symmetry>
     <cml:atomArray>
      <cml:atom id="a1" elementType="C" x3="-0.484730822094136E-05" y3="0.130348928542146E-01"
        z3="0.716963443603513"/>
      <cml:atom id="a2" elementType="H" x3="0.434415498783322E-02" y3="-1.00054084164564"
        z3="1.09568734985573"/>
      <cml:atom id="a3" elementType="H" x3="0.882618720068626" y3="0.523615665216855"
        z3="1.0981002165673"/>
      <cml:atom id="a4" elementType="H" x3="-0.886766561391341" y3="0.516264774482607"
        z3="1.09839487958002"/>
      <cml:atom id="a5" elementType="O" x3="-0.814342093909773E-05" y3="-0.630334465695629E-01"
        z3="-0.679872117216907"/>
      <cml:atom id="a6" elementType="H" x3="-0.935562809302422E-05" y3="0.805842443093595"
        z3="-1.03888251481289"/>
     </cml:atomArray>
     <cml:bondArray>
      <cml:bond atomRefs2="a1 a2"/>
      <cml:bond atomRefs2="a1 a3"/>
      <cml:bond atomRefs2="a1 a4"/>
      <cml:bond atomRefs2="a1 a5"/>
      <cml:bond atomRefs2="a5 a6"/>
     </cml:bondArray>
    </cml:molecule>
    <property name="Energy" method="RHF" principal="true" stateSymmetry="1" stateNumber="1"
      value="-115.07581143677"/>
    <property name="One-electron energy" method="RHF" value="-237.891295278964"/>
    <property name="Two-electron energy" method="RHF" value="81.9962288762171"/>
    <property name="Kinetic energy" method="RHF" value="115.115077907995"/>
    <property name="Nuclear energy" method="RHF" value="40.8192549659775"/>
    <property name="Virial quotient" method="RHF" value="-0.999658893761456"/>
    <property name="Dipole moment" method="RHF" principal="true" stateSymmetry="1"
      stateNumber="1"
      value="-0.401933754888063 0.513188320572981 0.306665038046161"/>
    <time start="11:12:22" end="11:12:24" cpu="4.51" system="0.11" real="3.61"/>
    <storage units="megabyte" memory="0.0" sf="0.06" df="177.37" eaf="31.29" ga="0.0"/>
    <summary overall_method="HF/6-311G(D,P)"/>
   </jobstep>
   <gradient name="SCF GRADIENT" stateSymmetry="1" stateNumber="1"
     virial="0.97510498025417E-03">
      0.000032081924   0.000024749266  -0.000336608551
      0.000040422898  -0.000036202323   0.000000989985
      0.000031311436   0.000066393380   0.000035675199
     -0.000100347710  -0.000027903410   0.000032522811
      0.000335769822  -0.000530274195   0.000542549394
     -0.000339238370   0.000503237281  -0.000275128837
   </gradient>
   <opt energy="-115.07581144" type="HF-SCF000" line="0.0"
     convergence="0.331183139902427E-02" gradient="0.112640052613166E-02"/>
   <jobstep command="HF-SCF" commandset="SCFPRO">
    <cml:molecule>
     <cml:symmetry pointGroup="C1">
     </cml:symmetry>
     <cml:atomArray>
      <cml:atom id="a1" elementType="C" x3="0.541363338254659E-05" y3="0.130291748626697E-01"
        z3="0.717105209955396"/>
      <cml:atom id="a2" elementType="H" x3="0.145853381441562E-02" y3="-1.00053429251975"
        z3="1.09569491920336"/>
      <cml:atom id="a3" elementType="H" x3="0.88387807299841" y3="0.521249596177964"
        z3="1.09824698686516"/>
      <cml:atom id="a4" elementType="H" x3="-0.885452925520579" y3="0.51861886411293"
        z3="1.09813272391435"/>
      <cml:atom id="a5" elementType="O" x3="0.66603219298524E-05" y3="-0.629998986286097E-01"
        z3="-0.679963324106278"/>
      <cml:atom id="a6" elementType="H" x3="-0.538446146792709E-04" y3="0.805383526492935"
        z3="-1.03901516736187"/>
     </cml:atomArray>
     <cml:bondArray>
      <cml:bond atomRefs2="a1 a2"/>
      <cml:bond atomRefs2="a1 a3"/>
      <cml:bond atomRefs2="a1 a4"/>
      <cml:bond atomRefs2="a1 a5"/>
      <cml:bond atomRefs2="a5 a6"/>
     </cml:bondArray>
    </cml:molecule>
    <property name="Energy" method="RHF" principal="true" stateSymmetry="1" stateNumber="1"
      value="-115.075811963755"/>
    <property name="One-electron energy" method="RHF" value="-237.890566340451"/>
    <property name="Two-electron energy" method="RHF" value="81.9957967026998"/>
    <property name="Kinetic energy" method="RHF" value="115.115877506006"/>
    <property name="Nuclear energy" method="RHF" value="40.8189576739964"/>
    <property name="Virial quotient" method="RHF" value="-0.999651954681499"/>
    <property name="Dipole moment" method="RHF" principal="true" stateSymmetry="1"
      stateNumber="1"
      value="-0.403286123662363 0.512007033013422 0.307075955703452"/>
    <time start="11:12:26" end="11:12:29" cpu="5.51" system="0.1" real="4.92"/>
    <storage units="megabyte" memory="0.0" sf="0.06" df="177.37" eaf="31.29" ga="0.0"/>
    <summary overall_method="HF/6-311G(D,P)"/>
   </jobstep>
   <gradient name="SCF GRADIENT" stateSymmetry="1" stateNumber="1"
     virial="0.178361377299187E-03">
      0.000028444505   0.000042205894  -0.000090090750
      0.000011016990  -0.000018812788  -0.000017571698
      0.000014936037   0.000024812965   0.000013601129
     -0.000043796353  -0.000023191408  -0.000006581662
      0.000064870478  -0.000140233618   0.000156254214
     -0.000075471656   0.000115218955  -0.000055611233
   </gradient>
   <opt energy="-115.07581196" type="HF-SCF000" line="0.0"
     convergence="0.160287572769461E-02" gradient="0.292176117167391E-03"/>
   <jobstep command="HF-SCF" commandset="SCFPRO">
    <cml:molecule>
     <cml:symmetry pointGroup="C1">
     </cml:symmetry>
     <cml:atomArray>
      <cml:atom id="a1" elementType="C" x3="-0.360254790636915E-06" y3="0.130166631292641E-01"
        z3="0.717166289899882"/>
      <cml:atom id="a2" elementType="H" x3="-0.587399773834932E-04" y3="-1.00046800048113"
        z3="1.09589553438961"/>
      <cml:atom id="a3" elementType="H" x3="0.884615569111366" y3="0.519937769056952"
        z3="1.09818335451305"/>
      <cml:atom id="a4" elementType="H" x3="-0.884533714095811" y3="0.52006277329881"
        z3="1.09821940611182"/>
      <cml:atom id="a5" elementType="O" x3="-0.17749799336198E-05" y3="-0.629943455353567E-01"
        z3="-0.680017847716404"/>
      <cml:atom id="a6" elementType="H" x3="0.934466641757476E-05" y3="0.805245995863333"
        z3="-1.0391007718145"/>
     </cml:atomArray>
     <cml:bondArray>
      <cml:bond atomRefs2="a1 a2"/>
      <cml:bond atomRefs2="a1 a3"/>
      <cml:bond atomRefs2="a1 a4"/>
      <cml:bond atomRefs2="a1 a5"/>
      <cml:bond atomRefs2="a5 a6"/>
     </cml:bondArray>
    </cml:molecule>
    <property name="Energy" method="RHF" principal="true" stateSymmetry="1" stateNumber="1"
      value="-115.075812016116"/>
    <property name="One-electron energy" method="RHF" value="-237.888861782196"/>
    <property name="Two-electron energy" method="RHF" value="81.9949400270309"/>
    <property name="Kinetic energy" method="RHF" value="115.116045161276"/>
    <property name="Nuclear energy" method="RHF" value="40.8181097390491"/>
    <property name="Virial quotient" method="RHF" value="-0.999650499240971"/>
    <property name="Dipole moment" method="RHF" principal="true" stateSymmetry="1"
      stateNumber="1"
      value="-0.404060842821733 0.511390420033654 0.307289185219325"/>
    <time start="11:12:31" end="11:12:34" cpu="5.26" system="0.11" real="5.04"/>
    <storage units="megabyte" memory="0.0" sf="0.06" df="177.37" eaf="31.29" ga="0.0"/>
    <summary overall_method="HF/6-311G(D,P)"/>
   </jobstep>
   <jobstep command="HF-SCF" commandset="SCFPRO">
    <cml:molecule>
     <cml:symmetry pointGroup="C1">
     </cml:symmetry>
     <cml:atomArray>
      <cml:atom id="a1" elementType="C" x3="-0.36025479063447E-06" y3="0.130166631292641E-01"
        z3="0.717166289899881"/>
      <cml:atom id="a2" elementType="H" x3="-0.587399773834907E-04" y3="-1.00046800048113"
        z3="1.09589553438961"/>
      <cml:atom id="a3" elementType="H" x3="0.884615569111366" y3="0.519937769056952"
        z3="1.09818335451305"/>
      <cml:atom id="a4" elementType="H" x3="-0.884533714095811" y3="0.52006277329881"
        z3="1.09821940611182"/>
      <cml:atom id="a5" elementType="O" x3="-0.177497993361735E-05" y3="-0.629943455353567E-01"
        z3="-0.680017847716404"/>
      <cml:atom id="a6" elementType="H" x3="0.934466641757721E-05" y3="0.805245995863333"
        z3="-1.0391007718145"/>
     </cml:atomArray>
     <cml:bondArray>
      <cml:bond atomRefs2="a1 a2"/>
      <cml:bond atomRefs2="a1 a3"/>
      <cml:bond atomRefs2="a1 a4"/>
      <cml:bond atomRefs2="a1 a5"/>
      <cml:bond atomRefs2="a5 a6"/>
     </cml:bondArray>
    </cml:molecule>
    <property name="Energy" method="RHF" principal="true" stateSymmetry="1" stateNumber="1"
      value="-115.075812015862"/>
    <property name="One-electron energy" method="RHF" value="-237.888861340293"/>
    <property name="Two-electron energy" method="RHF" value="81.9949395853819"/>
    <property name="Kinetic energy" method="RHF" value="115.116045015354"/>
    <property name="Nuclear energy" method="RHF" value="40.8181097390491"/>
    <property name="Virial quotient" method="RHF" value="-0.999650500505931"/>
    <property name="Dipole moment" method="RHF" principal="true" stateSymmetry="1"
      stateNumber="1"
      value="0.682898576171932E-05 0.611982571872748 0.380380346474149"/>
    <time start="11:12:34" end="11:12:38" cpu="4.55" system="0.09" real="4.53"/>
    <storage units="megabyte" memory="0.0" sf="0.06" df="177.37" eaf="31.29" ga="0.0"/>
    <summary overall_method="HF/6-311G(D,P)"/>
   </jobstep>
   <time start="11:10:56" end="11:12:38" cpu="108.77" system="2.19" real="102.16"/>
   <storage units="megabyte" memory="0.0" sf="0.06" df="177.37" eaf="31.29" ga="0.0"/>
   <summary overall_method="HF/6-311G(D,P)//HF/6-311G(D,P)"/>
  </jobstep>
  <jobstep command="FREQ" commandset="FREQ">
   <cml:molecule>
    <cml:symmetry pointGroup="C1">
    </cml:symmetry>
    <cml:atomArray>
     <cml:atom id="a1" elementType="C" x3="-0.360254790632295E-06" y3="0.130166631292641E-01"
       z3="0.717166289899881"/>
     <cml:atom id="a2" elementType="H" x3="-0.587399773834886E-04" y3="-1.00046800048113"
       z3="1.09589553438961"/>
     <cml:atom id="a3" elementType="H" x3="0.884615569111366" y3="0.519937769056952"
       z3="1.09818335451305"/>
     <cml:atom id="a4" elementType="H" x3="-0.884533714095811" y3="0.52006277329881"
       z3="1.09821940611182"/>
     <cml:atom id="a5" elementType="O" x3="-0.177497993361518E-05" y3="-0.629943455353567E-01"
       z3="-0.680017847716404"/>
     <cml:atom id="a6" elementType="H" x3="0.934466641757938E-05" y3="0.805245995863333"
       z3="-1.0391007718145"/>
    </cml:atomArray>
    <cml:bondArray>
     <cml:bond atomRefs2="a1 a2"/>
     <cml:bond atomRefs2="a1 a3"/>
     <cml:bond atomRefs2="a1 a4"/>
     <cml:bond atomRefs2="a1 a5"/>
     <cml:bond atomRefs2="a5 a6"/>
    </cml:bondArray>
   </cml:molecule>
   <vibrations>
    <normalCoordinate wavenumber="4186.49" units="inverseCentimetre" IRintensity="0.0"
      IRintensityunits="km/mol" symmetry="A" real_zero_imag="R">
     -0.00000002 -0.00167938 -0.00074173
      0.00000070  0.01061184 -0.00407596
      0.00043554  0.00053367 -0.00232898
     -0.00043603  0.00053433 -0.00232907
     -0.00000070 -0.05552977  0.02484281
      0.00001122  0.88961386 -0.37670767
    </normalCoordinate>
    <normalCoordinate wavenumber="3256.97" units="inverseCentimetre" IRintensity="0.0"
      IRintensityunits="km/mol" symmetry="A" real_zero_imag="R">
     -0.00000895 -0.08481219  0.01691733
      0.00005010  0.86569905 -0.30999045
      0.14552828  0.06677986  0.05561071
     -0.14547186  0.06677481  0.05559640
      0.00000003  0.00148520 -0.00001206
     -0.00000039 -0.01298063 -0.00245710
    </normalCoordinate>
    <normalCoordinate wavenumber="3184.9" units="inverseCentimetre" IRintensity="0.0"
      IRintensityunits="km/mol" symmetry="A" real_zero_imag="R">
     -0.08984845 -0.00000016 -0.00001253
     -0.02300077 -0.00011771  0.00004216
      0.54226339  0.32389481  0.22162618
      0.54186045 -0.32377351 -0.22150343
      0.00050184 -0.00000021 -0.00000090
      0.00072259  0.00000162 -0.00000143
    </normalCoordinate>
    <normalCoordinate wavenumber="3140.53" units="inverseCentimetre" IRintensity="0.0"
      IRintensityunits="km/mol" symmetry="A" real_zero_imag="R">
     -0.00002683  0.03022304  0.04097104
      0.00000714  0.25415022 -0.08914219
     -0.55119197 -0.30456318 -0.21795415
      0.55149918 -0.30485455 -0.21811818
      0.00000027 -0.00019761  0.00202406
      0.00000077 -0.00145681  0.00525607
    </normalCoordinate>
    <normalCoordinate wavenumber="1630.35" units="inverseCentimetre" IRintensity="0.0"
      IRintensityunits="km/mol" symmetry="A" real_zero_imag="R">
     -0.00000348  0.04158227  0.04727497
      0.00008951  0.06172284  0.14468573
      0.40117217 -0.39664246 -0.36724332
     -0.40121933 -0.39649769 -0.36729155
     -0.00000003  0.01651448  0.00740638
     -0.00000036 -0.02579237 -0.09059050
    </normalCoordinate>
    <normalCoordinate wavenumber="1618.89" units="inverseCentimetre" IRintensity="0.0"
      IRintensityunits="km/mol" symmetry="A" real_zero_imag="R">
     -0.05698245 -0.00000159  0.00000590
      0.70635094 -0.00007807 -0.00008705
      0.05916343 -0.36941353  0.29439473
      0.05929481  0.36954539 -0.29437379
     -0.00856928 -0.00000262 -0.00000157
     -0.01032833  0.00000666  0.00002074
    </normalCoordinate>
    <normalCoordinate wavenumber="1615.29" units="inverseCentimetre" IRintensity="0.0"
      IRintensityunits="km/mol" symmetry="A" real_zero_imag="R">
     -0.00000456  0.02046395 -0.10001747
      0.00008982  0.25814768  0.58674363
     -0.01467832 -0.29059286  0.37769926
      0.01466000 -0.29052752  0.37763732
     -0.00000109  0.00536145 -0.00719116
      0.00000015 -0.00577817 -0.03706046
    </normalCoordinate>
    <normalCoordinate wavenumber="1488.85" units="inverseCentimetre" IRintensity="0.0"
      IRintensityunits="km/mol" symmetry="A" real_zero_imag="R">
      0.00000416  0.10973782 -0.01143647
     -0.00001053 -0.02152266 -0.37694367
      0.09196591 -0.17208693  0.15577539
     -0.09198570 -0.17208232  0.15580740
     -0.00000093 -0.07319667 -0.02877083
     -0.00000443  0.22074645  0.65814680
    </normalCoordinate>
    <normalCoordinate wavenumber="1277.07" units="inverseCentimetre" IRintensity="0.0"
      IRintensityunits="km/mol" symmetry="A" real_zero_imag="R">
      0.12185401 -0.00000113  0.00002036
     -0.24963174  0.00000617 -0.00001877
     -0.16502300  0.08303377  0.56466864
     -0.16506684 -0.08303915 -0.56460108
     -0.05453171  0.00000102 -0.00001661
     -0.00571578 -0.00000356 -0.00002751
    </normalCoordinate>
    <normalCoordinate wavenumber="1179.34" units="inverseCentimetre" IRintensity="0.0"
      IRintensityunits="km/mol" symmetry="A" real_zero_imag="R">
      0.00001168 -0.00895360 -0.19430222
     -0.00002281  0.00632530 -0.14269729
     -0.00318800 -0.00236701 -0.16669165
      0.00315730 -0.00237816 -0.16681568
     -0.00000499  0.00803535  0.16863490
     -0.00000640 -0.02249794  0.11337032
    </normalCoordinate>
    <normalCoordinate wavenumber="1159.82" units="inverseCentimetre" IRintensity="0.0"
      IRintensityunits="km/mol" symmetry="A" real_zero_imag="R">
      0.00000050 -0.06874747 -0.00356883
     -0.00000187  0.13241963  0.52975924
     -0.03636595  0.19402564 -0.26739112
      0.03636918  0.19402245 -0.26745512
     -0.00000082  0.00247265 -0.03330516
      0.00000568  0.25885390  0.57615731
    </normalCoordinate>
    <normalCoordinate wavenumber="342.28" units="inverseCentimetre" IRintensity="0.0"
      IRintensityunits="km/mol" symmetry="A" real_zero_imag="R">
      0.00433053  0.00000081 -0.00000123
      0.28075590 -0.00001603 -0.00000420
     -0.09693417  0.21119384 -0.04672098
     -0.09696362 -0.21117647  0.04671933
     -0.06285552 -0.00000006  0.00000099
      0.85914156 -0.00001005  0.00000481
    </normalCoordinate>
    <normalCoordinate wavenumber="0.0" units="inverseCentimetre" IRintensity="0.0"
      IRintensityunits="km/mol" symmetry="Err" real_zero_imag="Z">
      0.21808622 -0.06941926 -0.02336036
      0.12620537 -0.08718299 -0.07091052
      0.33978018 -0.21138579 -0.11702173
      0.33980250  0.03677544  0.11787060
      0.02192259 -0.00385600 -0.02692700
      0.09603806  0.01299246  0.01381382
    </normalCoordinate>
    <normalCoordinate wavenumber="0.0" units="inverseCentimetre" IRintensity="0.0"
      IRintensityunits="km/mol" symmetry="Err" real_zero_imag="Z">
      0.08766990  0.17510300  0.04720152
      0.25094480  0.24122964  0.22418250
      0.04277978  0.36283938 -0.09834843
      0.04276498  0.12045252  0.01568467
      0.00800948 -0.06887697  0.06047485
     -0.13409876 -0.13157940 -0.09114016
    </normalCoordinate>
    <normalCoordinate wavenumber="0.0" units="inverseCentimetre" IRintensity="0.0"
      IRintensityunits="km/mol" symmetry="Err" real_zero_imag="Z">
      0.03568470 -0.06326145  0.09230873
      0.36780240 -0.10620489 -0.02255732
     -0.08825386  0.15899843  0.08435582
     -0.08828871 -0.37187110  0.21518059
     -0.04481438  0.09509776  0.08369359
     -0.33189622  0.13580026  0.18210086
    </normalCoordinate>
    <normalCoordinate wavenumber="0.0" units="inverseCentimetre" IRintensity="0.0"
      IRintensityunits="km/mol" symmetry="Err" real_zero_imag="Z">
      0.02256131  0.10810217 -0.04703194
      0.03427768  0.08798056 -0.10087586
     -0.01418050  0.11598318  0.02778714
     -0.01418642  0.05973928 -0.06798014
      0.10061510  0.18232670 -0.05107005
      0.09245255  0.20140311 -0.00494471
    </normalCoordinate>
    <normalCoordinate wavenumber="0.0" units="inverseCentimetre" IRintensity="0.0"
      IRintensityunits="km/mol" symmetry="Err" real_zero_imag="Z">
     -0.00255652 -0.05069744  0.08736224
     -0.05164194 -0.05310742  0.08090555
     -0.05732927 -0.04999782  0.21359855
     -0.05733472 -0.05624566 -0.03241093
      0.19199830 -0.04180747  0.08687841
      0.23886470 -0.03952267  0.09240437
    </normalCoordinate>
    <normalCoordinate wavenumber="0.0" units="inverseCentimetre" IRintensity="0.0"
      IRintensityunits="km/mol" symmetry="Err" real_zero_imag="Z">
     -0.01048220  0.04988918  0.10046843
     -0.36553198  0.04443812  0.08582658
      0.18320398 -0.27484885  0.08282796
      0.18325010  0.36358651  0.13275704
     -0.07734244  0.07007713  0.09937021
      0.22584722  0.07526139  0.11191481
    </normalCoordinate>
   </vibrations>
   <time start="11:12:38" end="11:13:37" cpu="68.98" system="0.51" real="58.49"/>
   <storage units="megabyte" memory="0.0" sf="1.06" df="177.37" eaf="31.29" ga="0.0"/>
   <summary overall_method="HF/6-311G(D,P)//HF/6-311G(D,P)"/>
  </jobstep>
  <stm:metadataList>
   <stm:metadata name="dc:date" content="2025-08-25T11:13:37+02:00"/>
   <stm:metadata name="dc:creator" content="zwa"/>
   <stm:metadata name="cmlm:insilico" content="Molpro"/>
  </stm:metadataList>
  <platform>
   <version major="2022" minor="2" SHA="51306cdc306ce2a111a2867affebcb289530e0a7"
     integer_bits="64" parallelism="mpp">
    2022.2
    <date year="2025" month="8" day="25" hour="11" minute="10" second="52">
     2025-08-25T11:10:52
    </date>
   </version>
   <licence id="liedlgroup"/>
   <parallel processes="6" nodes="1" all_processes="6" openmp="8"/>
   <dimensions natom="400" nvalence="500" nvalence_pno="1000" nbasis="12000" nstate="100"
     nsymm="16" nrec="512" nprim="2" ncol="100"/>
  </platform>
  <input>
   <p>memory,1000,m</p>
   <p>orient,mass</p>
   <p>geometry = {</p>
   <p> C,                 -5.13924038 ,   0.99999999  ,  0.00000000</p>
   <p> H,                 -4.78258595 ,  -0.00881002  ,  0.00000000</p>
   <p> H,                 -4.78256754 ,   1.50439818  ,  0.87365150</p>
   <p> H,                 -6.20924038 ,   1.00001317  ,  0.00000000</p>
   <p> O,                 -4.66256546 ,   1.67410224  , -1.16759033</p>
   <p> H,                 -4.03197131 ,   3.20418707  , -1.55668147</p>
   <p>}</p>
   <p>mass,iso</p>
   <p>basis=6-311g(d,p)</p>
   <p>{hf</p>
   <p>start,atden}</p>
   <p>optg</p>
   <p>{frequencies, symm=auto,print=0,analytical}</p>
   <p>put,molden,methanol.molden</p>
  </input>
  <diagnostics warnings="0"/>
 </job>
</molpro>
